MANIFEST.in
README.md
setup.py
Orange3_DataFusion.egg-info/PKG-INFO
Orange3_DataFusion.egg-info/SOURCES.txt
Orange3_DataFusion.egg-info/dependency_links.txt
Orange3_DataFusion.egg-info/entry_points.txt
Orange3_DataFusion.egg-info/namespace_packages.txt
Orange3_DataFusion.egg-info/not-zip-safe
Orange3_DataFusion.egg-info/requires.txt
Orange3_DataFusion.egg-info/top_level.txt
orangecontrib/__init__.py
orangecontrib/datafusion/__init__.py
orangecontrib/datafusion/models.py
orangecontrib/datafusion/movielens.py
orangecontrib/datafusion/datasets/actors.csv
orangecontrib/datafusion/datasets/movies.csv
orangecontrib/datafusion/datasets/ratings.csv
orangecontrib/datafusion/tutorials/510-collective-tri-factorization.ows
orangecontrib/datafusion/tutorials/510-latent-factors.ows
orangecontrib/datafusion/tutorials/510-tri-factorization.ows
orangecontrib/datafusion/tutorials/__init__.py
orangecontrib/datafusion/widgets/__init__.py
orangecontrib/datafusion/widgets/graphview.py
orangecontrib/datafusion/widgets/owchaining.py
orangecontrib/datafusion/widgets/owcompletionscoring.py
orangecontrib/datafusion/widgets/owfusiongraph.py
orangecontrib/datafusion/widgets/owimdbactors.py
orangecontrib/datafusion/widgets/owlatentfactors.py
orangecontrib/datafusion/widgets/owmeanfuser.py
orangecontrib/datafusion/widgets/owmoviegenres.py
orangecontrib/datafusion/widgets/owmovieratings.py
orangecontrib/datafusion/widgets/owsamplematrix.py
orangecontrib/datafusion/widgets/owtabletorelation.py
orangecontrib/datafusion/widgets/icons/Category-Fusion.svg
orangecontrib/datafusion/widgets/icons/CompletionScoring.svg
orangecontrib/datafusion/widgets/icons/FusionGraph.svg
orangecontrib/datafusion/widgets/icons/IMDbActors.svg
orangecontrib/datafusion/widgets/icons/LatentChaining.svg
orangecontrib/datafusion/widgets/icons/LatentFactors.svg
orangecontrib/datafusion/widgets/icons/MatrixSampler.svg
orangecontrib/datafusion/widgets/icons/MeanFuser.svg
orangecontrib/datafusion/widgets/icons/MovieGenres.svg
orangecontrib/datafusion/widgets/icons/MovieRatings.svg
orangecontrib/datafusion/widgets/icons/TableToRelation.svg