Metadata-Version: 1.0
Name: Orange3-DataFusion
Version: 0.1.10
Summary: Orange DataFusion add-on.
Home-page: https://github.com/biolab/orange3-datafusion
Author: Bioinformatics Laboratory, FRI UL
Author-email: contact@orange.biolab.si
License: UNKNOWN
Keywords: data mining,orange3 add-on
Platform: UNKNOWN
